{"d9HbTFt+cg2mtb2IiQqsRA==":"mbr-2000x1333.jpg","p4651Cpj5eluMNb1OIa2xQ==":"mbr-1-2000x1333.jpg","ZPeIMmCaXWr4SZZ/EOGJVA==":"mbr-1400x933.jpg","usl9/jsRS+WltprlN6dGkg==":"mbr-1400x913.jpg","b7nN2gaFXVh7CqYyBmk28g==":"mbr-1400x1117.jpg","u6Wrmb3QVtXeLxR+77OAlQ==":"mbr-1400x1115.jpg","KVZzd6Wiq+KECrdb88aLkw==":"mbr-1400x1750.jpg","J39GASPU1lXWqfRAO7fAFA==":"mbr-1400x961.jpg","K9waUHR6wP0fD3nGSsatBw==":"mbr-1400x933.jpg","yC5kEcLz+/f+tIe+J+DB7w==":"mbr-2000x3000.jpg","GkFIOoHARl72DtmMXiea8w==":"mbr-2000x1333.jpg","jwY9vFeyCHI5Kc+2OK12eA==":"mbr-1-1400x933.jpg","IQlYr9pOpHKW0R9OyztpnQ==":"mbr-1400x2486.jpg","DPOZBft8zpqPGTwLJWIM5w==":"mbr-102x128.jpg","b6Pz+ABEQhOen4FEK5A4Zg==":"mbr-2-2000x1333.jpg"}